{
  "lastUpdated": "2026-02-06T00:00:00Z",
  "stats": {
    "activeAgents": 0,
    "spawnedToday": 0,
    "tasksDone": 0,
    "timeActive": "0:00",
    "focusProject": "-",
    "eventsToday": 0
  },
  "workflow": {
    "pending": [],
    "active": [],
    "review": [],
    "done": []
  },
  "projects": {
    "A": {
      "name": "Ambition",
      "subtitle": "By Calbee (Personal)",
      "projects": [
        {"id": "A1", "name": "Personal Tasks", "status": "pending", "progress": 0, "tasks": []},
        {"id": "A2", "name": "Re:Unite", "status": "active", "progress": 25, "tasks": []},
        {"id": "A3", "name": "KOE", "status": "pending", "progress": 0, "tasks": []},
        {"id": "A4", "name": "Streaming", "status": "pending", "progress": 0, "tasks": []},
        {"id": "A5", "name": "Trading", "status": "pending", "progress": 0, "tasks": []}
      ]
    },
    "B": {
      "name": "Business",
      "subtitle": "Empire (Main Work)",
      "projects": [
        {"id": "B1", "name": "Exstatic", "status": "pending", "progress": 0, "tasks": []},
        {"id": "B2", "name": "Energize", "status": "pending", "progress": 0, "tasks": []},
        {"id": "B3", "name": "Team Elevate", "status": "active", "progress": 10, "tasks": []},
        {"id": "B4", "name": "Pesta Fiesta", "status": "pending", "progress": 0, "tasks": []},
        {"id": "B5", "name": "Enticipate", "status": "pending", "progress": 0, "tasks": []},
        {"id": "B6", "name": "Elluminate", "status": "pending", "progress": 0, "tasks": []},
        {"id": "B7", "name": "Encompasse", "status": "pending", "progress": 0, "tasks": []},
        {"id": "B8", "name": "Empyrean", "status": "pending", "progress": 0, "tasks": []},
        {"id": "B9", "name": "Ethereal", "status": "pending", "progress": 0, "tasks": []},
        {"id": "B10", "name": "Epitaph", "status": "pending", "progress": 0, "tasks": []}
      ]
    },
    "C": {
      "name": "Callings",
      "subtitle": "On The Side (Other Jobs)",
      "projects": [
        {"id": "C1", "name": "Real Estate", "status": "pending", "progress": 0, "tasks": []},
        {"id": "C2", "name": "Side Sales Jobs", "status": "pending", "progress": 0, "tasks": []}
      ]
    }
  },
  "tasks": [],
  "decisions": [],
  "activity": [],
  "agents": [],
  "calendar": {
    "past": [],
    "today": [],
    "future": []
  }
}